fsp/__init__.py
fsp/fsp.py
fsp-0.0.1.10.dist-info/LICENCE
fsp-0.0.1.10.dist-info/METADATA
fsp-0.0.1.10.dist-info/WHEEL
fsp-0.0.1.10.dist-info/top_level.txt
fsp-0.0.1.10.dist-info/RECORD
