Metadata-Version: 2.1
Name: fsp
Version: 0.0.1.10
Summary: Pacote para auxiliar a realização de consultas SQL, para aqueles com pouco conhecimento sobre a linguagem.
Home-page: https://github.com/WanderleiSI/fsp.git
Author: José Wanderlei Francisco de Sousa Rocha
Author-email: wanderleirochavasco@hotmail.com
Classifier: Programming Language :: Python :: 3
Classifier: License :: OSI Approved :: GNU General Public License v3 (GPLv3)
Classifier: Operating System :: OS Independent
Requires-Python: >=3
License-File: LICENCE
